thorlabs_mc2000b/__init__.py
thorlabs_mc2000b-0.1.3.dist-info/LICENSE.txt
thorlabs_mc2000b-0.1.3.dist-info/METADATA
thorlabs_mc2000b-0.1.3.dist-info/WHEEL
thorlabs_mc2000b-0.1.3.dist-info/top_level.txt
thorlabs_mc2000b-0.1.3.dist-info/RECORD
