Metadata-Version: 2.1
Name: thorlabs-mc2000b
Version: 0.1.3
Summary: Interface to the ThorLabs MC2000B optical chopper.
Home-page: https://gitlab.com/ptapping/thorlabs-mc2000b
Author: Patrick Tapping
Author-email: mail@patricktapping.com
License: UNKNOWN
Project-URL: Source, https://gitlab.com/ptapping/thorlabs-mc2000b
Project-URL: Tracker, https://gitlab.com/ptapping/thorlabs-mc2000b/-/issues
Platform: UNKNOWN
Classifier: Programming Language :: Python :: 3
Classifier: License :: OSI Approved :: GNU General Public License v3 or later (GPLv3+)
Classifier: Operating System :: OS Independent
Requires-Python: >=3.6
Requires-Dist: pyserial
